sarif_pydantic/__init__.py
sarif_pydantic/_version.py
sarif_pydantic/sarif.py
sarif_pydantic-0.6.2.dist-info/METADATA
sarif_pydantic-0.6.2.dist-info/WHEEL
sarif_pydantic-0.6.2.dist-info/licenses/LICENSE
sarif_pydantic-0.6.2.dist-info/RECORD
