Metadata-Version: 2.4
Name: sarif-pydantic
Version: 0.6.2
Author-email: Daniel D'Avella <drdavella@gmail.com>
License-File: LICENSE
Requires-Python: >=3.10
Requires-Dist: pydantic>=2.8.0
